sinbadflow/__init__.py
sinbadflow/element.py
sinbadflow/executor.py
sinbadflow/agents/__init__.py
sinbadflow/agents/base_agent.py
sinbadflow/agents/databricks.py
sinbadflow/settings/__init__.py
sinbadflow/settings/dbr_settings.py
sinbadflow/settings/dbr_vars.py
sinbadflow/settings/settings.py
sinbadflow/utils/__init__.py
sinbadflow/utils/applier.py
sinbadflow/utils/dbr_job.py
sinbadflow/utils/logger.py
sinbadflow/utils/status_handler.py
sinbadflow-0.7.dist-info/LICENSE
sinbadflow-0.7.dist-info/METADATA
sinbadflow-0.7.dist-info/WHEEL
sinbadflow-0.7.dist-info/top_level.txt
sinbadflow-0.7.dist-info/RECORD
