Metadata-Version: 2.1
Name: sinbadflow
Version: 0.7
Summary: A simple pipeline creation and execution tool
Home-page: https://github.com/Eimisas/sinbadflow
Author: Eimantas Jazonis, Robertas Sys, Emilija Lamanauskaite
Author-email: eimant.jaz@gmail.com, robertas.sys@gmail.com, emilijalamanauskaite@gmail.com
License: UNKNOWN
Platform: UNKNOWN
Classifier: Programming Language :: Python :: 3
Classifier: License :: OSI Approved :: MIT License
Classifier: Operating System :: OS Independent
Requires-Python: >=3.6
Requires-Dist: mock (>=2)
Requires-Dist: setuptools (>=40.8)
Requires-Dist: forbiddenfruit (>=0.1.3)
